dagster_plus/__init__.py
dagster_plus-0.0.1.dist-info/LICENSE.md
dagster_plus-0.0.1.dist-info/METADATA
dagster_plus-0.0.1.dist-info/WHEEL
dagster_plus-0.0.1.dist-info/top_level.txt
dagster_plus-0.0.1.dist-info/RECORD
